fawoc/__init__.py
fawoc/fawoc.py
fawoc/terms.py
fawoc/utils.py
fawoc/version.py
fawoc-0.12.3.dist-info/LICENSE
fawoc-0.12.3.dist-info/METADATA
fawoc-0.12.3.dist-info/WHEEL
fawoc-0.12.3.dist-info/entry_points.txt
fawoc-0.12.3.dist-info/top_level.txt
fawoc-0.12.3.dist-info/RECORD
