Metadata-Version: 2.1
Name: fawoc
Version: 0.12.3
Summary: Fast Word Classifier
Home-page: https://github.com/robolab-pavia/fawoc
Author: Tullio Facchinetti
Author-email: tullio.facchinetti@unipv.it
License: GPL-3
Platform: UNKNOWN
Classifier: Programming Language :: Python :: 3
Classifier: Operating System :: OS Independent
License-File: LICENSE
Requires-Dist: prompt-toolkit
Requires-Dist: slrkit-utils
